create.py
addpip-1.0.6.dist-info/METADATA
addpip-1.0.6.dist-info/WHEEL
addpip-1.0.6.dist-info/top_level.txt
addpip-1.0.6.dist-info/RECORD
