Metadata-Version: 2.4
Name: addpip
Version: 1.0.6
Summary: Simplify making PyPI packages.
Requires-Dist: readme-md>=2018.11.23
